{
    "_updated": "2021-08-03",
    "label": "王法仏法相依",
    "objectID": "75243",
    "ページ番号": [
        "202"
    ],
    "ローマ字1": [
        "ōbō buppō sōi"
    ],
    "ローマ字2": [
        "obo buppo soi"
    ],
    "本": [
        "The Seven Tengu Scrolls: Evil and the Rhetoric of Legitimacy in Medieval Japanese Buddhism . University of Hawai'i Press . 2012"
    ],
    "著者": [
        "Wakabayashi, Haruko"
    ],
    "見出し読み": [
        "おうぼうぶっぽうそうい"
    ],
    "説明文": [
        "Mutual dependence between the Law of the Sovereign and the Law of the Buddha."
    ]
}