{
    "_updated": "2021-08-03",
    "label": "編木",
    "objectID": "75298",
    "ページ番号": [
        "105"
    ],
    "ローマ字1": [
        "binzasara"
    ],
    "ローマ字1_mod": [
        "binzasara"
    ],
    "ローマ字2": [
        "binzasara"
    ],
    "本": [
        "The Seven Tengu Scrolls: Evil and the Rhetoric of Legitimacy in Medieval Japanese Buddhism . University of Hawai'i Press . 2012"
    ],
    "著者": [
        "Wakabayashi, Haruko"
    ],
    "見出し読み": [
        "びんざさら"
    ],
    "見出し読み_mod": [
        "びんざさら"
    ],
    "説明文": [
        "Serpentine rattles."
    ]
}