{
    "_updated": "2021-08-03",
    "label": "上卿",
    "objectID": "75480",
    "ページ番号": [
        "33, 198"
    ],
    "ローマ字1": [
        "shōkei"
    ],
    "ローマ字2": [
        "shokei"
    ],
    "本": [
        "From Sovereign to Symbol: An Age of Ritual Determinism in Fourteenth Century Japan . Oxford University Press . 2012"
    ],
    "著者": [
        "Conlan, Thomas Donald"
    ],
    "見出し読み": [
        "しょうけい"
    ],
    "説明文": [
        "A noble in charge of a meeting, ritual, or an event. A courtier in charge"
    ]
}