{
    "_updated": "2021-08-03",
    "label": "朝堂",
    "objectID": "75748",
    "ページ番号": [
        "37"
    ],
    "ローマ字1": [
        "chōdō"
    ],
    "ローマ字1_mod": [
        "chōdō"
    ],
    "ローマ字2": [
        "chodo"
    ],
    "本": [
        "The Comparative Study of the Ritsuryo Bureaucracy in Ancient Japan and T'ang China. ACTA ASIATICA, 99 . The Tōhō Gakkai . 2010-08"
    ],
    "著者": [
        "Sakaue, Yasutoshi"
    ],
    "見出し読み": [
        "ちょうどう"
    ],
    "見出し読み_mod": [
        "ちょうどう"
    ],
    "説明文": [
        "Audience halls."
    ]
}