{
    "_updated": "2021-08-03",
    "label": "天変地異",
    "objectID": "76628",
    "ローマ字1": [
        "tenpenchii"
    ],
    "ローマ字1_mod": [
        "tenpenchii"
    ],
    "ローマ字2": [
        "tenpenchii"
    ],
    "対訳語": [
        "weather and earthquake related oddities- natural disasters"
    ],
    "本": [
        "USC Kambun Workshop 2007"
    ],
    "著者": [
        "Robinson, Matthew (compiler); Piggott, Joan R. (ed.)"
    ],
    "見出し読み": [
        "てんぺんちい"
    ],
    "見出し読み_mod": [
        "てんぺんちい"
    ]
}