{
    "_updated": "2021-08-03",
    "label": "史　",
    "objectID": "76818",
    "ページ番号": [
        "422"
    ],
    "ローマ字1": [
        "fuhito"
    ],
    "ローマ字2": [
        "fuhito"
    ],
    "本": [
        "Capital and Countryside in Japan, 300-1180:  Japanese Historians Interpreted in English . Cornell University East Asia Program . 2006"
    ],
    "著者": [
        "Piggott, Joan R.(ed.)"
    ],
    "見出し読み": [
        "ふひと"
    ],
    "説明文": [
        "a scribe, many of which served in various ritsuryô offices. [律令]"
    ]
}