{
    "_updated": "2021-08-03",
    "label": "下剋上",
    "objectID": "77493",
    "ページ番号": [
        "398"
    ],
    "ローマ字1": [
        "gekokujō"
    ],
    "ローマ字1_mod": [
        "gekokujō"
    ],
    "ローマ字2": [
        "gekokujo"
    ],
    "本": [
        "State of War: the Violent Order of Fourteenth Century Japan . Michigan University Press . 2003"
    ],
    "著者": [
        "Conlan, Thomas"
    ],
    "見出し読み": [
        "げこくじょう"
    ],
    "見出し読み_mod": [
        "げこくじょう"
    ],
    "説明文": [
        "A term describing the lower conquering the higher. Although often used to describe the Warring States\" turmoil of the sixteenth century, early in the fourteenth century this term was used to criticize how members of the Kamakura bakufu had usurped prerogatives of the court.\""
    ]
}