{
    "_updated": "2021-08-03",
    "label": "沙弥",
    "objectID": "77838",
    "ページ番号": [
        "167"
    ],
    "ローマ字1": [
        "Shami"
    ],
    "ローマ字2": [
        "shami"
    ],
    "本": [
        "The Moneylenders of Late Medieval Kyoto . University of Hawai'i Press . 2001"
    ],
    "著者": [
        "Gay, Suzanne"
    ],
    "見出し読み": [
        "しゃみ"
    ],
    "説明文": [
        "Either novice or laymen with only rudimentary training as priests without progressing beyond the novice stage."
    ]
}