{
    "label": "網代屏風",
    "objectID": "78129",
    "ページ番号": [
        "1135"
    ],
    "ローマ字1": [
        "ajiro byōbu"
    ],
    "ローマ字2": [
        "ajirobyobu"
    ],
    "対訳語": [
        "basketwork screen"
    ],
    "本": [
        "The Tale of Genji (Penguin Classics) . Viking Adult . 2001"
    ],
    "著者": [
        "Tyler, Royall"
    ],
    "見出し読み": [
        "あじろびょうぶ"
    ],
    "説明文": [
        "Screens made of woven slats of cypress (hinoki) or cryptomeria (sugi) wood. [檜、杉] [RK]"
    ]
}