{
    "_updated": "2021-08-03",
    "label": "春日神社",
    "objectID": "78385",
    "ページ番号": [
        "1143"
    ],
    "ローマ字1": [
        "Kasuga Jinja"
    ],
    "ローマ字1_mod": [
        "Kasuga Jinja"
    ],
    "ローマ字2": [
        "kasugajinja"
    ],
    "対訳語": [
        "Kasuga Shrine"
    ],
    "本": [
        "The Tale of Genji (Penguin Classics) . Viking Adult . 2001"
    ],
    "著者": [
        "Tyler, Royall"
    ],
    "見出し読み": [
        "かすがじんじゃ"
    ],
    "見出し読み_mod": [
        "かすがじんじゃ"
    ],
    "説明文": [
        "In Nara, the ancestral shrine of the Fujiwara.[奈良、藤原][RK]"
    ]
}