{
    "_updated": "2021-08-03",
    "label": "朽葉",
    "objectID": "78447",
    "ページ番号": [
        "1157"
    ],
    "ローマ字1": [
        "kuchiba"
    ],
    "ローマ字1_mod": [
        "kuchiba"
    ],
    "ローマ字2": [
        "kuchiba"
    ],
    "対訳語": [
        "ochre"
    ],
    "本": [
        "The Tale of Genji (Penguin Classics) . Viking Adult . 2001"
    ],
    "著者": [
        "Tyler, Royall"
    ],
    "見出し読み": [
        "くちば"
    ],
    "見出し読み_mod": [
        "くちば"
    ],
    "説明文": [
        "The Japanese word means “dead leaves.” [RK]"
    ]
}