{
    "_updated": "2021-08-03",
    "label": "畳紙",
    "objectID": "78728",
    "ページ番号": [
        "1139"
    ],
    "ローマ字1": [
        "tatōgami"
    ],
    "ローマ字2": [
        "tatogami"
    ],
    "対訳語": [
        "folding paper"
    ],
    "本": [
        "The Tale of Genji (Penguin Classics) . Viking Adult . 2001"
    ],
    "著者": [
        "Tyler, Royall"
    ],
    "見出し読み": [
        "たとうがみ"
    ],
    "説明文": [
        "A kind of general-purpose paper often kept, folded up, in the front fold of one’s robe.  It could be used when necessary instead of letter paper. [Also 帖紙][RK]"
    ]
}