{
    "_updated": "2021-08-03",
    "label": "軟障",
    "objectID": "78840",
    "ページ番号": [
        "1137"
    ],
    "ローマ字1": [
        "zejō"
    ],
    "ローマ字1_mod": [
        "zejō"
    ],
    "ローマ字2": [
        "zejo"
    ],
    "対訳語": [
        "cloth panel"
    ],
    "本": [
        "The Tale of Genji (Penguin Classics) . Viking Adult . 2001"
    ],
    "著者": [
        "Tyler, Royall"
    ],
    "見出し読み": [
        "ぜじょう"
    ],
    "見出し読み_mod": [
        "ぜじょう"
    ],
    "説明文": [
        "A panel of cloth hung to protect someone from being seen.  It might have a scene painted on the inner side, towards the person concealed.[Also read zenjō][RK]"
    ]
}