{
    "_updated": "2021-08-03",
    "label": "切岸",
    "objectID": "78959",
    "ページ番号": [
        "53"
    ],
    "ローマ字1": [
        "kirigishi"
    ],
    "ローマ字1_mod": [
        "kirigishi"
    ],
    "ローマ字2": [
        "kirigishi"
    ],
    "対訳語": [
        "cliff"
    ],
    "本": [
        "The Distinctive Characteristics of the Environs of Kamakura as a Medieval City. ACTA ASIATICA, 81 . The Tōhō Gakkai . 2001-09"
    ],
    "著者": [
        "Ishii, Susumu"
    ],
    "見出し読み": [
        "きりぎし"
    ],
    "見出し読み_mod": [
        "きりぎし"
    ],
    "説明文": [
        "Hills in the shape of man-made cliffs which surround Kamakura, corresponding to the castle walls."
    ]
}