{
    "_updated": "2021-08-03",
    "label": "承平天慶の乱",
    "objectID": "81191",
    "ページ番号": [
        "61"
    ],
    "ローマ字1": [
        "Jōhei-Tengyō [no ran]"
    ],
    "ローマ字2": [
        "joheitengyonoran"
    ],
    "対訳語": [
        "Jōhei-Tengyō Distrubance"
    ],
    "本": [
        "The Cambridge History of Japan, Volume 2:  Heian Japan . Cambridge University Press . 1999"
    ],
    "著者": [
        "Shiveley, D. and W. McCullough (ed.)"
    ],
    "見出し読み": [
        "じょうへいてんぎょうのらん"
    ],
    "説明文": [
        "Discord of the Jōhei [931-38] and Tengyō[938-47] Eras.  The Masakado revolt and the Sumitomo piracy. [平将門、藤原純友]"
    ]
}