{
    "_updated": "2021-08-03",
    "label": "外記節",
    "objectID": "85016",
    "ページ番号": [
        "271"
    ],
    "ローマ字1": [
        "gekibushi"
    ],
    "ローマ字1_mod": [
        "gekibushi"
    ],
    "ローマ字2": [
        "geki bushi"
    ],
    "本": [
        "Edo Culture: Daily Life and Diversions in Urban Japan, 1600-1868 . University of Hawai'i Press . 1997"
    ],
    "著者": [
        "Nishiyama, Matsunosuke"
    ],
    "見出し読み": [
        "げきぶし"
    ],
    "見出し読み_mod": [
        "げきぶし"
    ],
    "説明文": [
        "A form of joruri recitation developed in Edo by Satsuma Geki around the 1860s. Geki bushi declined greatly in popularity after the 1740s.［薩摩外記］"
    ]
}