{
    "_updated": "2021-08-03",
    "label": "岡船",
    "objectID": "85642",
    "ページ番号": [
        "48"
    ],
    "ローマ字1": [
        "okabune"
    ],
    "ローマ字1_mod": [
        "okabune"
    ],
    "ローマ字2": [
        "okabune"
    ],
    "対訳語": [
        "ships of the interior"
    ],
    "本": [
        "The Making of a Japanese Periphery, 1750-1920 . University of California Press . 1995"
    ],
    "著者": [
        "Wigen, Kären"
    ],
    "見出し読み": [
        "おかぶね"
    ],
    "見出し読み_mod": [
        "おかぶね"
    ],
    "説明文": [
        "In negotiations with the post-station managers, Iida merchants consistently referred to peaant operators as okabune,\" or \"ships of the interior,\" a pointed reminder of the pack drivers' right to go anywhere they pleased.　\""
    ]
}