{
    "_updated": "2021-08-03",
    "label": "懐風藻",
    "objectID": "85819",
    "ページ番号": [
        "420"
    ],
    "ローマ字1": [
        "Kaifūsō"
    ],
    "ローマ字2": [
        "kaifuso"
    ],
    "対訳語": [
        "Fond recollections of poetry"
    ],
    "本": [
        "Sugawara no Michizane and the Early Heian Court . University of Hawai'i Press . 1994"
    ],
    "著者": [
        "Borgen, Robert"
    ],
    "見出し読み": [
        "かいふうそう"
    ],
    "説明文": [
        "Compiled in 751 and consisting of 116 poems, [the poems in Kaifūsō are] all written in the simplest of Chinese verse forms (p. 41)."
    ]
}