{
    "_updated": "2021-08-03",
    "label": "凌雲集",
    "objectID": "85885",
    "ページ番号": [
        "426"
    ],
    "ローマ字1": [
        "Ryōunshū"
    ],
    "ローマ字1_mod": [
        "Ryōunshū"
    ],
    "ローマ字2": [
        "ryounshu"
    ],
    "対訳語": [
        "Cloud-borne collection"
    ],
    "本": [
        "Sugawara no Michizane and the Early Heian Court . University of Hawai'i Press . 1994"
    ],
    "著者": [
        "Borgen, Robert"
    ],
    "見出し読み": [
        "りょううんしゅう"
    ],
    "見出し読み_mod": [
        "りょううんしゅう"
    ],
    "説明文": [
        "The first imperial kanshi anthology (compiled under the order of Emperor Saga).  Most of the Ryōunshū's ninety poems followed the elaborate T'ang rules for tone patterns and thus were in the contemporary Chinese style (p. 42). [漢詩、嵯峨天皇]"
    ]
}