{
    "_updated": "2021-08-03",
    "label": "陣",
    "objectID": "86418",
    "ページ番号": [
        "222"
    ],
    "ローマ字1": [
        "Jin"
    ],
    "ローマ字2": [
        "jin"
    ],
    "対訳語": [
        "Battalion"
    ],
    "本": [
        "Hired Swords . Stanford University Press . 1992"
    ],
    "著者": [
        "Friday, Karl F."
    ],
    "見出し読み": [
        "じん"
    ],
    "説明文": [
        "The largest subdivisions of the ritsuryō expeditionary armies; battalions were the tactical equivalents of the regiments, which were administrative units. [律令] [HW]"
    ]
}