{
    "_updated": "2021-08-03",
    "label": "大鏡",
    "objectID": "89802",
    "ページ番号": [
        "876"
    ],
    "ローマ字1": [
        "Ōkagami"
    ],
    "ローマ字1_mod": [
        "Ōkagami"
    ],
    "ローマ字2": [
        "okagami"
    ],
    "対訳語": [
        "Great Mirror"
    ],
    "本": [
        "A Tale of Flowering Fortunes:  Annals of Japanese Aristocratic Life in the Heian Period (Volumes One and Two) . Stanford University Press . 1980"
    ],
    "著者": [
        "McCullough, William and Helen"
    ],
    "見出し読み": [
        "おおかがみ"
    ],
    "見出し読み_mod": [
        "おおかがみ"
    ]
}