{
    "_updated": "2021-08-03",
    "label": "茱萸",
    "objectID": "89994",
    "ページ番号": [
        "900"
    ],
    "ローマ字1": [
        "shuyu"
    ],
    "ローマ字1_mod": [
        "shuyu"
    ],
    "ローマ字2": [
        "shuyu"
    ],
    "対訳語": [
        "rue"
    ],
    "本": [
        "A Tale of Flowering Fortunes:  Annals of Japanese Aristocratic Life in the Heian Period (Volumes One and Two) . Stanford University Press . 1980"
    ],
    "著者": [
        "McCullough, William and Helen"
    ],
    "見出し読み": [
        "しゅゆ"
    ],
    "見出し読み_mod": [
        "しゅゆ"
    ]
}