{
    "_updated": "2021-08-03",
    "label": "寄進状",
    "objectID": "91179",
    "ページ番号": [
        "201"
    ],
    "ローマ字1": [
        "kishinjō"
    ],
    "ローマ字1_mod": [
        "kishinjō"
    ],
    "ローマ字2": [
        "kishinjo"
    ],
    "本": [
        "The Kamakura Bakufu:  A Study in Documents . Stanford University Press . 1976"
    ],
    "著者": [
        "Mass, Jeffrey P."
    ],
    "見出し読み": [
        "きしんじょう"
    ],
    "見出し読み_mod": [
        "きしんじょう"
    ],
    "説明文": [
        "A document for the commendation (endowment) of land. A kishinjō conveyed ownership rights to some higher authority, such as a temple or noble house, often preparatory to shōen incorporation. As a result of such commendations, donors were generally confirmed in a managerialcustodial authority, and recipients became proprietors (ryōke).　[領家]"
    ]
}