{
    "label": "王政復古",
    "objectID": "91550",
    "ローマ字1": [
        "ōsei-fukko"
    ],
    "ローマ字2": [
        "osei-fukko"
    ],
    "対訳語": [
        "The restoration of imperial rule. Term for the overthrow of the Bakufu and the resumption by the Emperor of direct responsibility for the government of the country."
    ],
    "本": [
        "The Meiji Restoration . Stanford University Press . 1972"
    ],
    "著者": [
        "Beasley, William G."
    ],
    "見出し読み": [
        "おうせいふっこ"
    ]
}