{
    "label": "主油司",
    "objectID": "91679",
    "ページ番号": [
        "94"
    ],
    "ローマ字1": [
        "Abura-no-tsukasa"
    ],
    "ローマ字2": [
        "aburanotsukasa"
    ],
    "対訳語": [
        "Oil Office."
    ],
    "本": [
        "Early Japanese History c. 40 B.C.-A.D. 1167,  Part B . Princeton University Press . 1937"
    ],
    "著者": [
        "Reischauer, Jean and Robert"
    ],
    "見出し読み": [
        "あぶらのつかさ"
    ],
    "説明文": [
        "An office under the Ministry of the Imperial Household (Kunaishō). In charge of animal, vegetable, and mineral oils sent in from the provinces (kuni). [宮内省、国]"
    ]
}