{
    "_updated": "2021-08-03",
    "label": "足柄峠",
    "objectID": "91812",
    "ページ番号": [
        "98"
    ],
    "ローマ字1": [
        "Ashigara-tōge"
    ],
    "ローマ字1_mod": [
        "Ashigara tōge"
    ],
    "ローマ字2": [
        "asigaratoge"
    ],
    "本": [
        "Early Japanese History c. 40 B.C.-A.D. 1167,  Part B . Princeton University Press . 1937"
    ],
    "著者": [
        "Reischauer, Jean and Robert"
    ],
    "見出し読み": [
        "あしがらとうげ"
    ],
    "見出し読み_mod": [
        "あしがらとうげ"
    ],
    "説明文": [
        "a mountain pass from Sagami-no-kuni into Izu-no-kuni. [相模国、伊豆国]"
    ]
}