{
    "label": "円満院",
    "objectID": "92170",
    "ページ番号": [
        "118"
    ],
    "ローマ字1": [
        "Emman-in"
    ],
    "ローマ字2": [
        "enmanin"
    ],
    "本": [
        "Early Japanese History c. 40 B.C.-A.D. 1167,  Part B . Princeton University Press . 1937"
    ],
    "著者": [
        "Reischauer, Jean and Robert"
    ],
    "見出し読み": [
        "えんまんいん"
    ],
    "説明文": [
        "Buddhist temple, being one of the building of the Onjō-ji. In Shiga-no-kōri, Ōmi-no-kuni. [園城寺、滋賀郡、近江国]"
    ]
}