{
    "_updated": "2021-08-03",
    "label": "葵",
    "objectID": "74430",
    "ページ番号": [
        "302"
    ],
    "ローマ字1": [
        "afuhi"
    ],
    "ローマ字1_mod": [
        "afuhi"
    ],
    "ローマ字2": [
        "afuhi"
    ],
    "対訳語": [
        "mallow"
    ],
    "本": [
        "Rice, Agriculture, and the Food Supply in Premodern Japan . Routledge . 2016"
    ],
    "著者": [
        "Von Verschuer, Charlotte"
    ],
    "見出し読み": [
        "あふひ"
    ],
    "見出し読み_mod": [
        "あふひ"
    ],
    "説明文": [
        "Malvaceae. Malva verticillata."
    ]
}