{
    "_updated": "2021-08-03",
    "label": "徳政",
    "objectID": "75495",
    "ページ番号": [
        "199"
    ],
    "ローマ字1": [
        "tokusei"
    ],
    "ローマ字2": [
        "tokusei"
    ],
    "本": [
        "From Sovereign to Symbol: An Age of Ritual Determinism in Fourteenth Century Japan . Oxford University Press . 2012"
    ],
    "著者": [
        "Conlan, Thomas Donald"
    ],
    "見出し読み": [
        "とくせい"
    ],
    "説明文": [
        "Lit. Virtuous government,\" a policy of debt relief which was initially enacted by emperor Go-Saga.\""
    ]
}