{
    "_updated": "2021-08-03",
    "label": "謹啓",
    "objectID": "75614",
    "ページ番号": [
        "44"
    ],
    "ローマ字1": [
        "kinkei"
    ],
    "ローマ字1_mod": [
        "kinkei"
    ],
    "ローマ字2": [
        "kinkei"
    ],
    "本": [
        "The Adoption of the Ritsuryo Codes and Their Civilizing Influence. ACTA ASIATICA, 99 . The Tōhō Gakkai . 2010-08"
    ],
    "著者": [
        "Maruyama, Yumiko"
    ],
    "見出し読み": [
        "きんけい"
    ],
    "見出し読み_mod": [
        "きんけい"
    ],
    "説明文": [
        "Opening and closing phrases in documents."
    ]
}