{
    "_updated": "2021-08-03",
    "label": "違勅罪",
    "objectID": "75810",
    "ローマ字1": [
        "ichokuzai"
    ],
    "ローマ字2": [
        "ichokuzai"
    ],
    "対訳語": [
        "The crime of disobeying orders, treason"
    ],
    "本": [
        "USC Kambun Workshop 2008"
    ],
    "著者": [
        "Wilson, Kevin (compiler); Piggott, Joan R. (ed.)"
    ],
    "見出し読み": [
        "いちょくざい"
    ],
    "説明文": [
        "These are acts that do not conform to a royal command. An act of treason under the ritsuryō codes. [律令]"
    ]
}