{
    "_updated": "2021-08-03",
    "label": "獻",
    "objectID": "76494",
    "ローマ字1": [
        "kon"
    ],
    "ローマ字1_mod": [
        "kon"
    ],
    "ローマ字2": [
        "kon"
    ],
    "対訳語": [
        "round"
    ],
    "本": [
        "USC Kambun Workshop 2007"
    ],
    "著者": [
        "Robinson, Matthew (compiler); Piggott, Joan R. (ed.)"
    ],
    "見出し読み": [
        "こん"
    ],
    "見出し読み_mod": [
        "こん"
    ],
    "説明文": [
        "When used in reference to drinking parties, it is a counter for rounds of drinks, as in ikkon （いっこん）, nikon（にこん）, and sankon（さんこん）.  [一獻、二獻、三獻]"
    ]
}