{
    "_updated": "2021-08-03",
    "label": "渤海存問使",
    "objectID": "76685",
    "ローマ字1": [
        "bokkai zonmonshi"
    ],
    "ローマ字1_mod": [
        "bokkai zonmonshi"
    ],
    "ローマ字2": [
        "bokkaizonmonshi"
    ],
    "対訳語": [
        "Agent to Verify and Greet the Bohai Embassy"
    ],
    "本": [
        "USC Kambun Workshop 2007"
    ],
    "著者": [
        "Robinson, Matthew (compiler); Piggott, Joan R. (ed.)"
    ],
    "見出し読み": [
        "ぼっかいぞんもんし"
    ],
    "見出し読み_mod": [
        "ぼっかいぞんもんし"
    ]
}