{
    "_updated": "2021-08-03",
    "label": "興国",
    "objectID": "78056",
    "ページ番号": [
        "244-249"
    ],
    "ローマ字1": [
        "KŌKOKU"
    ],
    "ローマ字1_mod": [
        "KŌKOKU"
    ],
    "ローマ字2": [
        "kokoku"
    ],
    "本": [
        "日本史総合年表[Nihonshi Sōgō Nenpyō] . Yoshikawa kōbunkan . 2001"
    ],
    "著者": [
        "Tomoyasu Kato,Seiitiro Seno,Yasushi Toriumi,Yasunari Maruyama"
    ],
    "見出し読み": [
        "こうこく"
    ],
    "見出し読み_mod": [
        "こうこく"
    ],
    "説明文": [
        "AD1340～1346↓CH至元（zhi4-yuan2）6～至正（zhi4-zheng4）6"
    ]
}