{
    "_updated": "2021-08-03",
    "label": "内匠寮",
    "objectID": "78720",
    "ページ番号": [
        "1147"
    ],
    "ローマ字1": [
        "Takumizukasa"
    ],
    "ローマ字2": [
        "takumizukasa"
    ],
    "対訳語": [
        "Office of Artisans"
    ],
    "本": [
        "The Tale of Genji (Penguin Classics) . Viking Adult . 2001"
    ],
    "著者": [
        "Tyler, Royall"
    ],
    "見出し読み": [
        "たくみずかさ"
    ],
    "説明文": [
        "An office under the Bureau of Central Affairs, responsible for making  and maintaining the furniture and furnishings in the palace. [RK]"
    ]
}