{
    "_updated": "2021-08-03",
    "label": "土倉",
    "objectID": "78903",
    "ページ番号": [
        "12"
    ],
    "ローマ字1": [
        "dosō"
    ],
    "ローマ字1_mod": [
        "dosō"
    ],
    "ローマ字2": [
        "doso"
    ],
    "本": [
        "Commerce and Finance in the Middle Ages: The Beginnings of 'Capitalism'. ACTA ASIATICA, 81 . The Tōhō Gakkai . 2001-09"
    ],
    "著者": [
        "Amino, Yoshihiko"
    ],
    "見出し読み": [
        "どそう"
    ],
    "見出し読み_mod": [
        "どそう"
    ],
    "説明文": [
        "moneylenders"
    ]
}