{
    "_updated": "2021-08-03",
    "label": "獅子",
    "objectID": "79171",
    "ページ番号": [
        "38"
    ],
    "ローマ字1": [
        "Shishi"
    ],
    "ローマ字2": [
        "shishi"
    ],
    "対訳語": [
        "Lion"
    ],
    "本": [
        "Exhibition of Shōsō-in Treasures , The 52nd  . Nara National Museum . 2000"
    ],
    "著者": [
        "Nara National Museum"
    ],
    "見出し読み": [
        "しし"
    ],
    "説明文": [
        "Usually translated as lion, the shishi actually [is] a mythical Chinese animal with lionlike characteristics."
    ]
}