{
    "_updated": "2021-08-03",
    "label": "院北面",
    "objectID": "81171",
    "ページ番号": [
        "745"
    ],
    "ローマ字1": [
        "in-no-hokumen"
    ],
    "ローマ字1_mod": [
        "in no hokumen"
    ],
    "ローマ字2": [
        "innohokumen"
    ],
    "本": [
        "The Cambridge History of Japan, Volume 2:  Heian Japan . Cambridge University Press . 1999"
    ],
    "著者": [
        "Shiveley, D. and W. McCullough (ed.)"
    ],
    "見出し読み": [
        "いんのほくめん"
    ],
    "見出し読み_mod": [
        "いんのほくめん"
    ],
    "説明文": [
        "See hokumen. [北面]"
    ]
}