{
    "label": "武者",
    "objectID": "81280",
    "ページ番号": [
        "749"
    ],
    "ローマ字1": [
        "musha"
    ],
    "ローマ字2": [
        "musha"
    ],
    "対訳語": [
        "martial one"
    ],
    "本": [
        "The Cambridge History of Japan, Volume 2:  Heian Japan . Cambridge University Press . 1999"
    ],
    "著者": [
        "Shiveley, D. and W. McCullough (ed.)"
    ],
    "見出し読み": [
        "むしゃ"
    ],
    "説明文": [
        "A Sino-Japanese binom for the Japanese warrior.  Also musa."
    ]
}