{
    "_updated": "2021-08-03",
    "label": "凌雲集",
    "objectID": "81328",
    "ページ番号": [
        "356"
    ],
    "ローマ字1": [
        "Ryōunshū"
    ],
    "ローマ字1_mod": [
        "Ryōunshū"
    ],
    "ローマ字2": [
        "ryounshu"
    ],
    "本": [
        "The Cambridge History of Japan, Volume 2:  Heian Japan . Cambridge University Press . 1999"
    ],
    "著者": [
        "Shiveley, D. and W. McCullough (ed.)"
    ],
    "見出し読み": [
        "りょううんしゅう"
    ],
    "見出し読み_mod": [
        "りょううんしゅう"
    ],
    "説明文": [
        "Imperial anthology of poems in Chinese (814), containing 90 poems, and compiled chiefly by Ono no Munemori (778-830) (p. 357). [小野岑守]"
    ]
}