{
    "label": "宮内省",
    "objectID": "84847",
    "ページ番号": [
        "318"
    ],
    "ローマ字1": [
        "Kunaishō"
    ],
    "ローマ字2": [
        "kunaisho"
    ],
    "対訳語": [
        "the Ministry of the Royal Household"
    ],
    "本": [
        "The Emergence of Japanese Kingship . Stanford University Press . 1997"
    ],
    "著者": [
        "Piggott, Joan R."
    ],
    "見出し読み": [
        "くないしょう"
    ],
    "説明文": [
        "the Ministry of the Royal Household established by the ritsuryō codes. [律令]"
    ]
}