{
    "_updated": "2021-08-03",
    "label": "中興",
    "objectID": "85208",
    "ページ番号": [
        "374"
    ],
    "ローマ字1": [
        "chūkō"
    ],
    "ローマ字2": [
        "chuko"
    ],
    "対訳語": [
        "Restoration"
    ],
    "本": [
        "Kenmu . Harvard University Asia Center . 1996"
    ],
    "著者": [
        "Goble, Andrew E."
    ],
    "見出し読み": [
        "ちゅうこう"
    ],
    "説明文": [
        "A traditional Chinese and Confucian term that suggests an intermediate and morally worthy effort to revitalize an old imperial polity that is nevertheless ultimately fated to disappear (p. xii). [HW]"
    ]
}