{
    "_updated": "2021-08-03",
    "label": "嫡子",
    "objectID": "86386",
    "ページ番号": [
        "219"
    ],
    "ローマ字1": [
        "Chakushi"
    ],
    "ローマ字2": [
        "chakushi"
    ],
    "対訳語": [
        "Designated principal heir."
    ],
    "本": [
        "Hired Swords . Stanford University Press . 1992"
    ],
    "著者": [
        "Friday, Karl F."
    ],
    "見出し読み": [
        "ちゃくし"
    ],
    "説明文": [
        "Chakushi succeeded their fathers as heads of their families and inherited the most important hereditary rights and properties; they were usually, but not necessarily, the eldest sons."
    ]
}