{
    "_updated": "2021-08-03",
    "label": "下賜",
    "objectID": "86481",
    "ページ番号": [
        "234"
    ],
    "ローマ字1": [
        "kashi"
    ],
    "ローマ字1_mod": [
        "kashi"
    ],
    "ローマ字2": [
        "kashi"
    ],
    "対訳語": [
        "imperial grants"
    ],
    "本": [
        "Servants, Shophands, and Laborers in the Cities of Tokugawa Japan . Princeton University Press . 1992"
    ],
    "著者": [
        "Leupp, Gary P."
    ],
    "見出し読み": [
        "かし"
    ],
    "見出し読み_mod": [
        "かし"
    ]
}