{
    "_updated": "2021-08-03",
    "label": "足利義満",
    "objectID": "86658",
    "ページ番号": [
        "813"
    ],
    "ローマ字1": [
        "Ashikaga Yoshimitsu"
    ],
    "ローマ字1_mod": [
        "Ashikaga Yoshimitsu"
    ],
    "ローマ字2": [
        "ashikagayoshimitsu"
    ],
    "本": [
        "The Cambridge History of Japan, Volume 4:  Early Modern Japan . Cambridge University Press . 1991"
    ],
    "著者": [
        "Hall, John Whitney (ed.)"
    ],
    "見出し読み": [
        "あしかがよしみつ"
    ],
    "見出し読み_mod": [
        "あしかがよしみつ"
    ],
    "説明文": [
        "(1358-1408) [T]he third shogun of the Muromachi bakufu, who retained his control over Japan's foreign affairs even after formally retiring from the shogunate in 1395 (p. 235). [室町幕府]"
    ]
}