{
    "_updated": "2021-08-03",
    "label": "荘主",
    "objectID": "88738",
    "ページ番号": [
        "387"
    ],
    "ローマ字1": [
        "shōsu"
    ],
    "ローマ字1_mod": [
        "shōsu"
    ],
    "ローマ字2": [
        "shosu"
    ],
    "対訳語": [
        "Estate overseers"
    ],
    "本": [
        "Five Mountains: The Rinzai Zen Monastic Institution in Medieval Japan . Harvard University Press . 1981"
    ],
    "著者": [
        "Coｌlcutt, Martin"
    ],
    "見出し読み": [
        "しょうす"
    ],
    "見出し読み_mod": [
        "しょうす"
    ]
}