{
    "_updated": "2021-08-03",
    "label": "弁",
    "objectID": "89185",
    "ページ番号": [
        "867"
    ],
    "ローマ字1": [
        "ben"
    ],
    "ローマ字2": [
        "ben"
    ],
    "対訳語": [
        "Controller"
    ],
    "本": [
        "A Tale of Flowering Fortunes:  Annals of Japanese Aristocratic Life in the Heian Period (Volumes One and Two) . Stanford University Press . 1980"
    ],
    "著者": [
        "McCullough, William and Helen"
    ],
    "見出し読み": [
        "べん"
    ],
    "説明文": [
        "[Also benkan (弁官）]"
    ]
}