{
    "_updated": "2021-08-03",
    "label": "唐衣",
    "objectID": "89532",
    "ページ番号": [
        "882"
    ],
    "ローマ字1": [
        "Karaginu"
    ],
    "ローマ字1_mod": [
        "Karaginu"
    ],
    "ローマ字2": [
        "karaginu"
    ],
    "対訳語": [
        "woman's jacket"
    ],
    "本": [
        "A Tale of Flowering Fortunes:  Annals of Japanese Aristocratic Life in the Heian Period (Volumes One and Two) . Stanford University Press . 1980"
    ],
    "著者": [
        "McCullough, William and Helen"
    ],
    "見出し読み": [
        "からぎぬ"
    ],
    "見出し読み_mod": [
        "からぎぬ"
    ],
    "説明文": [
        "The outermost garment of a Heian lady's formal Court costume  (p. 225n)."
    ]
}