{
    "_updated": "2021-08-03",
    "label": "大嘗会",
    "objectID": "90241",
    "ローマ字1": [
        "Daijōe, or Daijōsai"
    ],
    "ローマ字1_mod": [
        "Daijōe, or Daijōsai"
    ],
    "ローマ字2": [
        "Daijoe, or Daijosai"
    ],
    "本": [
        "Japan's First Bureaucracy . Cornell University East Asia Program . 1978"
    ],
    "著者": [
        "Miller, Richard"
    ],
    "見出し読み": [
        "だいじょうえ,だいじょうさい"
    ],
    "見出し読み_mod": [
        "だいじょうえ,だいじょうさい"
    ],
    "説明文": [
        "Great New Food Festival at time of the enthronement. Also read Onie no matsuri."
    ]
}