{
    "_updated": "2021-08-03",
    "label": "閤門",
    "objectID": "90513",
    "ローマ字1": [
        "kōmon"
    ],
    "ローマ字1_mod": [
        "kōmon"
    ],
    "ローマ字2": [
        "komon"
    ],
    "本": [
        "Japan's First Bureaucracy . Cornell University East Asia Program . 1978"
    ],
    "著者": [
        "Miller, Richard"
    ],
    "見出し読み": [
        "こうもん"
    ],
    "見出し読み_mod": [
        "こうもん"
    ],
    "説明文": [
        "gates to the east and west of the imperial audience hall"
    ]
}