{
    "label": "注進状",
    "objectID": "91088",
    "ページ番号": [
        "195"
    ],
    "ローマ字1": [
        "chūshinjō"
    ],
    "ローマ字2": [
        "chushinjo"
    ],
    "本": [
        "The Kamakura Bakufu:  A Study in Documents . Stanford University Press . 1976"
    ],
    "著者": [
        "Mass, Jeffrey P."
    ],
    "見出し読み": [
        "ちゅうしんじょう"
    ],
    "説明文": [
        "A documentary form used to list something or to report to a higher authority. Tax registers (e.g. kechige or san'yōjō) are one type of chūshinjō.　[結解、散用状]"
    ]
}