{
    "_updated": "2021-08-03",
    "label": "解",
    "objectID": "92991",
    "ページ番号": [
        "299"
    ],
    "ローマ字1": [
        "ge"
    ],
    "ローマ字1_mod": [
        "ge"
    ],
    "ローマ字2": [
        "ge"
    ],
    "対訳語": [
        "petition; complaint"
    ],
    "本": [
        "[Historical Glossary Project 2.0 2017- (ed.)]"
    ],
    "見出し読み": [
        "げ"
    ],
    "見出し読み_mod": [
        "げ"
    ],
    "説明文": [
        "[Jeffrey P. Mass. Yoritomo and the Founding of the First Bakufu: The Origins of Dual Government in Japan. Stanford: Stanford University Press. 1999]"
    ]
}